LICENSE.md
MANIFEST.in
README.rst
setup.py
django_react_cms.egg-info/PKG-INFO
django_react_cms.egg-info/SOURCES.txt
django_react_cms.egg-info/dependency_links.txt
django_react_cms.egg-info/not-zip-safe
django_react_cms.egg-info/requires.txt
django_react_cms.egg-info/top_level.txt
react_cms/__init__.py
react_cms/admin.py
react_cms/apps.py
react_cms/models.py
react_cms/__pycache__/__init__.cpython-35.pyc
react_cms/__pycache__/admin.cpython-35.pyc
react_cms/__pycache__/models.cpython-35.pyc
react_cms/migrations/0001_initial.py
react_cms/migrations/0002_contentresource.py
react_cms/migrations/__init__.py
react_cms/migrations/__pycache__/0001_initial.cpython-35.pyc
react_cms/migrations/__pycache__/0002_contentresource.cpython-35.pyc
react_cms/migrations/__pycache__/__init__.cpython-35.pyc
react_cms/tests/__init__.py
react_cms/tests/runtests.py
react_cms/tests/__pycache__/__init__.cpython-35.pyc
react_cms/tests/__pycache__/test_execution.cpython-35.pyc
react_cms/tests/__pycache__/test_models.cpython-35.pyc
react_cms/tests/__pycache__/test_serializers.cpython-35.pyc
react_cms/tests/__pycache__/test_views.cpython-35.pyc