Metadata-Version: 1.1
Name: django-react-cms
Version: 0.1.0
Summary: Manage and export react components to the client.
Home-page: https://github.com/leonardoarroyo/django-react-cms
Author: Leonardo Arroyo
Author-email: contato@leonardoarroyo.com
License: MIT
Download-URL: https://github.com/leonardoarroyo/django-react-cms/tarball/0.1.0
Platform: UNKNOWN
